<?xml version="1.0" encoding="utf-8"?>
<RulePackage xmlns="http://schemas.microsoft.com/office/2011/mce">
  <RulePack id="7210bbc6-9495-46ed-9703-d2603e263560">
    <Version major="1" minor="0" build="0" revision="0" />
    <Publisher id="00000000-0000-0000-0000-000000000000" />
    <Details defaultLangCode="en-us">
      <LocalizedDetails langcode="en-us">
        <PublisherName>PurviewInsights SIT</PublisherName>
        <Name>Sanctions_Export_Control_References_ES</Name>
        <Description>Sanctions Export Control References - Spanish (Custom SIT for Microsoft Purview)</Description>
      </LocalizedDetails>
    </Details>
  </RulePack>
  <Rules>
    <Entity id="5edc7ed5-3437-40fc-926f-3570826f39a1" patternsProximity="300" recommendedConfidence="85">
      <Pattern confidenceLevel="85">
        <IdMatch idRef="Keyword_Primary_Sanctions_Export_Control_References_ES" />
        <Match idRef="Keyword_Context_Sanctions_Export_Control_References_ES" />
      </Pattern>
      <Pattern confidenceLevel="75">
        <IdMatch idRef="Keyword_Primary_Sanctions_Export_Control_References_ES" />
      </Pattern>
    </Entity>
    <Keyword id="Keyword_Primary_Sanctions_Export_Control_References_ES">
      <Group matchStyle="word">
      <Term>Sanción</Term>
      <Term>Sanctions</Term>
      <Term>Embargo</Term>
      <Term>Export Control</Term>
      <Term>Restricted Party</Term>
      <Term>Denied Entity</Term>
      <Term>Blocked Person</Term>
      <Term>SDN List</Term>
      <Term>OFAC</Term>
      <Term>EU Sanctions</Term>
      <Term>UN Sanctions</Term>
      <Term>UK Sanctions</Term>
      <Term>BIS</Term>
      <Term>EAR</Term>
      <Term>ITAR</Term>
      <Term>SECO</Term>
      <Term>Dual Use Goods</Term>
      </Group>
    </Keyword>    <Keyword id="Keyword_Context_Sanctions_Export_Control_References_ES">
      <Group matchStyle="word">
      <Term>Cumplimiento Screening</Term>
      <Term>KYC</Term>
      <Term>AML</Term>
      <Term>Export License</Term>
      <Term>License Application</Term>
      <Term>High Risk Country</Term>
      <Term>Restricted Country</Term>
      <Term>Transaction Screening</Term>
      <Term>Regulatorio</Term>
      </Group>
    </Keyword>
    <LocalizedStrings>
      <Resource idRef="5edc7ed5-3437-40fc-926f-3570826f39a1">
        <Name default="true" langcode="en-us">Sanctions_Export_Control_References_ES</Name>
        <Description default="true" langcode="en-us">Sanctions Export Control References - Spanish (Custom SIT for Microsoft Purview)</Description>
      </Resource>
    </LocalizedStrings>
  </Rules>
</RulePackage>
